{
  "jsonData": [
    {
      "담보명": "상해후유장해(3~100%)",
      "가입금액": "1000",
      "DB손해보험": 1170,
      "한화손해보험": 1330,
      "흥국화재": 960,
      "하나손해": 720,
      "현대해상화재": 940,
      "KB손해보험": 1090,
      "ABL생명": 1260,
      "DB생명": 810,
      "동양생명": 1633,
      "KB라이프": 1310,
      "미래에셋": 1270,
      "롯데손해보험": 760,
      "신한라이프": 1590,
      "농협손해": 858,
      "삼성화재": 1070
    },
    {
      "담보명": "상해고도후유(80%이상)",
      "가입금액": "1000",
      "DB손해보험": 190,
      "한화손해보험": 190,
      "흥국화재": 120,
      "하나손해": 120,
      "현대해상화재": 130,
      "KB손해보험": 150,
      "동양생명": 199,
      "메리츠화재": 130,
      "농협손해": 138,
      "삼성화재": 160
    },
    {
      "담보명": "상해사망",
      "가입금액": "1000",
      "DB손해보험": 1440,
      "한화손해보험": 1230,
      "흥국화재": 970,
      "하나손해": 900,
      "현대해상화재": 830,
      "KB손해보험": 1440,
      "DB생명": 1040,
      "흥국생명": 1720,
      "KB라이프": 1100,
      "미래에셋": 2990,
      "롯데손해보험": 1160,
      "신한라이프": 1830,
      "메리츠화재": 1040,
      "농협손해": 1282,
      "삼성화재": 1220
    },
    {
      "담보명": "질병후유장해(3~100%)",
      "가입금액": "1000",
      "DB손해보험": 110500,
      "한화손해보험": 62480,
      "흥국화재": 59360,
      "하나손해": 62990,
      "현대해상화재": 60190,
      "KB손해보험": 88790,
      "ABL생명": 164320,
      "DB생명": 18350,
      "동양생명": 15774,
      "한화생명": 22260,
      "흥국생명": 20300,
      "KB라이프": 23980,
      "미래에셋": 23410,
      "롯데손해보험": 60460,
      "신한라이프": 24590,
      "농협손해": 65549
    },
    {
      "담보명": "질병고도후유(80%이상)",
      "가입금액": "1000",
      "DB손해보험": 4040,
      "한화손해보험": 6790,
      "흥국화재": 6390,
      "하나손해": 7904,
      "현대해상화재": 6232,
      "KB손해보험": 11760,
      "메리츠화재": 3260,
      "농협손해": 5611,
      "삼성화재": 4200
    },
    {
      "담보명": "통합암진단비",
      "가입금액": "1000",
      "DB손해보험": 55610,
      "한화손해보험": 55538,
      "흥국화재": 59520,
      "하나손해": 54470,
      "현대해상화재": 78340,
      "KB손해보험": 55010,
      "DB생명": 35340,
      "한화생명": 67070,
      "KB라이프": 50400,
      "미래에셋": 54370,
      "롯데손해보험": 37510,
      "신한라이프": 54590,
      "메리츠화재": 40810,
      "농협손해": 64787,
      "삼성화재": 65080
    },
    {
      "담보명": "암진단비(유사암제외)",
      "가입금액": "3000",
      "DB손해보험": 103620,
      "한화손해보험": 112710,
      "흥국화재": 92220,
      "하나손해": 101580,
      "현대해상화재": 91980,
      "KB손해보험": 102000,
      "ABL생명": 73410,
      "DB생명": 75000,
      "동양생명": 69492,
      "한화생명": 101160,
      "흥국생명": 86700,
      "KB라이프": 80040,
      "미래에셋": 79080,
      "롯데손해보험": 93810,
      "신한라이프": 73581,
      "메리츠화재": 92670,
      "농협손해": 108171,
      "삼성화재": 101820
    },
    {
      "담보명": "고액암진단비",
      "가입금액": "1000",
      "DB손해보험": 6940,
      "하나손해": 5310,
      "KB손해보험": 3150,
      "동양생명": 1646,
      "흥국생명": 2500,
      "KB라이프": 2000,
      "미래에셋": 4810,
      "롯데손해보험": 5510,
      "신한라이프": 3200,
      "메리츠화재": 5150,
      "농협손해": 5370
    },
    {
      "담보명": "유사암진단비",
      "가입금액": "1000",
      "DB손해보험": 5200,
      "한화손해보험": 6800,
      "흥국화재": 5500,
      "하나손해": 3900,
      "현대해상화재": 5200,
      "KB손해보험": 4600,
      "ABL생명": 3880,
      "DB생명": 5690,
      "동양생명": 3770,
      "한화생명": 6300,
      "흥국생명": 4700,
      "KB라이프": 4880,
      "미래에셋": 5600,
      "롯데손해보험": 4200,
      "신한라이프": 5030,
      "메리츠화재": 2850,
      "농협손해": 11780,
      "삼성화재": 5600
    },
    {
      "담보명": "암주요치료비(10년)",
      "가입금액": "1000",
      "DB손해보험": 53124,
      "한화손해보험": 66574,
      "흥국화재": 50910,
      "하나손해": 49862,
      "현대해상화재": 53440,
      "ABL생명": 41396,
      "DB생명": 42600,
      "동양생명": 35494,
      "한화생명": 46050,
      "KB라이프": 54364,
      "미래에셋": 45744,
      "롯데손해보험": 47652,
      "신한라이프": 45828,
      "메리츠화재": 50636,
      "농협손해": 63440,
      "삼성화재": 51214
    },
    {
      "담보명": "암상급종합병원주요치료비(10년)",
      "가입금액": "1000",
      "DB손해보험": 33826,
      "한화손해보험": 44242,
      "하나손해": 32098,
      "현대해상화재": 38140,
      "ABL생명": 29808,
      "동양생명": 22854,
      "한화생명": 38090,
      "KB라이프": 38616,
      "미래에셋": 33034,
      "롯데손해보험": 34950,
      "신한라이프": 33394,
      "메리츠화재": 32622,
      "농협손해": 39700,
      "삼성화재": 32980
    },
    {
      "담보명": "항암방사선약물치료비(최초1회한)",
      "가입금액": "300",
      "DB손해보험": 5118,
      "한화손해보험": 9423,
      "흥국화재": 4578,
      "하나손해": 4284,
      "현대해상화재": 8556,
      "KB손해보험": 5697,
      "ABL생명": 492,
      "DB생명": 5610,
      "동양생명": 3937,
      "한화생명": 5571,
      "흥국생명": 3552,
      "KB라이프": 4614,
      "미래에셋": 3672,
      "롯데손해보험": 6333,
      "신한라이프": 3180,
      "메리츠화재": 4575,
      "농협손해": 6789,
      "삼성화재": 7482
    },
    {
      "담보명": "표적항암약물허가치료비(최초1회한)",
      "가입금액": "1000",
      "DB손해보험": 2370,
      "한화손해보험": 3690,
      "흥국화재": 1460,
      "하나손해": 2048,
      "현대해상화재": 3169,
      "KB손해보험": 2932,
      "ABL생명": 2200,
      "DB생명": 2190,
      "동양생명": 2765,
      "한화생명": 5276,
      "흥국생명": 2050,
      "KB라이프": 3910,
      "미래에셋": 1240,
      "롯데손해보험": 4294,
      "신한라이프": 1700,
      "메리츠화재": 2400,
      "농협손해": 1660,
      "삼성화재": 3620
    },
    {
      "담보명": "항암중입자방사선지료비(최초1회한)",
      "가입금액": "1000",
      "DB손해보험": 1710,
      "한화손해보험": 1960,
      "흥국화재": 1350,
      "하나손해": 1390,
      "현대해상화재": 906,
      "KB손해보험": 2140,
      "ABL생명": 1020,
      "DB생명": 1210,
      "동양생명": 594,
      "한화생명": 646,
      "흥국생명": 870,
      "KB라이프": 570,
      "미래에셋": 825,
      "롯데손해보험": 1310,
      "신한라이프": 730,
      "메리츠화재": 1260,
      "농협손해": 1260,
      "삼성화재": 1610
    },
    {
      "담보명": "하이클래스암주요치료비(10년)",
      "가입금액": "1000",
      "DB손해보험": 8630,
      "한화손해보험": 10970,
      "흥국화재": 7620,
      "하나손해": 8120,
      "현대해상화재": 9386,
      "KB손해보험": 8980,
      "ABL생명": 6960,
      "DB생명": 8690,
      "동양생명": 7040,
      "흥국생명": 9200,
      "KB라이프": 7780,
      "미래에셋": 7470,
      "롯데손해보험": 8220,
      "신한라이프": 8790,
      "메리츠화재": 8280,
      "농협손해": 11418,
      "삼성화재": 8450
    },
    {
      "담보명": "암수술비(매회,유사암포함)",
      "가입금액": "300",
      "DB손해보험": 15616,
      "한화손해보험": 15534,
      "흥국화재": 15576,
      "하나손해": 10632,
      "현대해상화재": 14760,
      "KB손해보험": 12483,
      "ABL생명": 1935,
      "DB생명": 10814,
      "동양생명": 11700,
      "흥국생명": 15870,
      "KB라이프": 10863,
      "미래에셋": 11835,
      "롯데손해보험": 13044,
      "신한라이프": 10290,
      "메리츠화재": 7836,
      "농협손해": 14652,
      "삼성화재": 13332
    },
    {
      "담보명": "다빈치로봇암수술비",
      "가입금액": "1000",
      "DB손해보험": 5000,
      "한화손해보험": 2698,
      "흥국화재": 2540,
      "하나손해": 2665,
      "현대해상화재": 3200,
      "KB손해보험": 2583,
      "DB생명": 3800,
      "동양생명": 3661,
      "한화생명": 9230,
      "흥국생명": 9530,
      "미래에셋": 4690,
      "롯데손해보험": 3440,
      "신한라이프": 7230,
      "메리츠화재": 4760,
      "농협손해": 8240,
      "삼성화재": 4200
    },
    {
      "담보명": "뇌혈관질환진단비",
      "가입금액": "1000",
      "DB손해보험": 28730,
      "한화손해보험": 35410,
      "흥국화재": 27100,
      "하나손해": 29670,
      "현대해상화재": 31180,
      "KB손해보험": 32220,
      "DB생명": 18260,
      "동양생명": 21445,
      "한화생명": 18600,
      "흥국생명": 17210,
      "KB라이프": 16420,
      "미래에셋": 19540,
      "롯데손해보험": 31570,
      "신한라이프": 20810,
      "메리츠화재": 25310,
      "농협손해": 27128,
      "삼성화재": 25500
    },
    {
      "담보명": "뇌졸중진단비",
      "가입금액": "1000",
      "DB손해보험": 20070,
      "한화손해보험": 26500,
      "흥국화재": 19990,
      "하나손해": 18450,
      "현대해상화재": 19450,
      "KB손해보험": 22260,
      "ABL생명": 7000,
      "DB생명": 11990,
      "한화생명": 13360,
      "흥국생명": 10850,
      "KB라이프": 13770,
      "롯데손해보험": 23340,
      "신한라이프": 11610,
      "메리츠화재": 17520,
      "농협손해": 25228,
      "삼성화재": 18300
    },
    {
      "담보명": "뇌출혈진단비",
      "가입금액": "1000",
      "DB손해보험": 4410,
      "한화손해보험": 5920,
      "흥국화재": 3930,
      "하나손해": 3910,
      "현대해상화재": 4090,
      "KB손해보험": 4830,
      "DB생명": 2340,
      "동양생명": 2300,
      "한화생명": 2640,
      "흥국생명": 2380,
      "KB라이프": 2780,
      "미래에셋": 3230,
      "롯데손해보험": 5324,
      "신한라이프": 2340,
      "메리츠화재": 4170,
      "농협손해": 4950,
      "삼성화재": 3620
    },
    {
      "담보명": "허혈성심장질환진단비",
      "가입금액": "1000",
      "DB손해보험": 13880,
      "한화손해보험": 25800,
      "흥국화재": 16010,
      "하나손해": 16500,
      "현대해상화재": 21400,
      "KB손해보험": 22510,
      "DB생명": 13600,
      "동양생명": 11454,
      "한화생명": 16960,
      "흥국생명": 16480,
      "KB라이프": 12600,
      "미래에셋": 15930,
      "롯데손해보험": 19730,
      "신한라이프": 19190,
      "메리츠화재": 17380,
      "농협손해": 13154,
      "삼성화재": 18100
    },
    {
      "담보명": "급성심근경색증진단비",
      "가입금액": "1000",
      "DB손해보험": 6350,
      "한화손해보험": 9760,
      "흥국화재": 6440,
      "하나손해": 6430,
      "현대해상화재": 6970,
      "KB손해보험": 7300,
      "ABL생명": 3310,
      "DB생명": 4350,
      "동양생명": 5194,
      "한화생명": 4770,
      "흥국생명": 4650,
      "KB라이프": 5190,
      "미래에셋": 5830,
      "롯데손해보험": 7554,
      "신한라이프": 4550,
      "메리츠화재": 7160,
      "농협손해": 8749,
      "삼성화재": 7180
    },
    {
      "담보명": "중증뇌심질환산정특례",
      "가입금액": "200",
      "DB손해보험": 14044,
      "한화손해보험": 15372,
      "흥국화재": 5180,
      "하나손해": 14016,
      "현대해상화재": 6778,
      "KB손해보험": 7070,
      "DB생명": 3278,
      "동양생명": 7298,
      "한화생명": 10140,
      "흥국생명": 9780,
      "미래에셋": 8490,
      "롯데손해보험": 11410,
      "신한라이프": 5108,
      "메리츠화재": 6786,
      "삼성화재": 4704
    },
    {
      "담보명": "순환계질환진단비",
      "가입금액": "1000",
      "DB손해보험": 73500,
      "흥국화재": 79960,
      "KB손해보험": 88600,
      "KB라이프": 77100,
      "미래에셋": 68720,
      "롯데손해보험": 74400,
      "메리츠화재": 116000,
      "농협손해": 73750,
      "삼성화재": 108740
    },
    {
      "담보명": "순환계주요치료비(10년)",
      "가입금액": "1000",
      "DB손해보험": 21060,
      "흥국화재": 18760,
      "롯데손해보험": 19420,
      "농협손해": 14850
    },
    {
      "담보명": "순환계주요치료비(만기보장)",
      "가입금액": "1000",
      "DB손해보험": 44590,
      "한화손해보험": 60240,
      "흥국화재": 48840,
      "하나손해": 75200,
      "KB손해보험": 47490,
      "흥국생명": 61660,
      "KB라이프": 49650,
      "롯데손해보험": 33290,
      "신한라이프": 54000,
      "농협손해": 31110
    },
    {
      "담보명": "순환계주요치료비(10년)상급종합병원",
      "가입금액": "1000",
      "DB손해보험": 9540,
      "롯데손해보험": 10130
    },
    {
      "담보명": "혈전용해치료비",
      "가입금액": "200",
      "DB손해보험": 602,
      "한화손해보험": 918,
      "흥국화재": 524,
      "하나손해": 558,
      "현대해상화재": 562,
      "KB손해보험": 1052,
      "ABL생명": 22,
      "DB생명": 202,
      "동양생명": 360,
      "흥국생명": 1012,
      "KB라이프": 312,
      "미래에셋": 514,
      "롯데손해보험": 632,
      "신한라이프": 864,
      "메리츠화재": 898,
      "농협손해": 572,
      "삼성화재": 490
    },
    {
      "담보명": "뇌혈관질환및허혈성심장질환수술비",
      "가입금액": "500",
      "DB손해보험": 8700,
      "한화손해보험": 15290,
      "흥국화재": 9400,
      "하나손해": 8035,
      "현대해상화재": 11350,
      "KB손해보험": 8865,
      "DB생명": 7625,
      "동양생명": 7330,
      "흥국생명": 10250,
      "KB라이프": 9505,
      "미래에셋": 5610,
      "롯데손해보험": 9550,
      "신한라이프": 7090,
      "메리츠화재": 7875,
      "농협손해": 6740,
      "삼성화재": 7430
    },
    {
      "담보명": "상해수술비",
      "가입금액": "10",
      "DB손해보험": 708,
      "한화손해보험": 1095,
      "흥국화재": 819,
      "하나손해": 966,
      "현대해상화재": 1129,
      "KB손해보험": 811,
      "ABL생명": 45,
      "동양생명": 472,
      "흥국생명": 772,
      "KB라이프": 591,
      "미래에셋": 424,
      "롯데손해보험": 836,
      "신한라이프": 594,
      "메리츠화재": 1004,
      "농협손해": 496,
      "삼성화재": 946
    },
    {
      "담보명": "질병수술비",
      "가입금액": "10",
      "DB손해보험": 11209,
      "한화손해보험": 6671,
      "흥국화재": 5594,
      "하나손해": 5194,
      "현대해상화재": 5913,
      "KB손해보험": 4878,
      "ABL생명": 462,
      "DB생명": 3777,
      "동양생명": 3642,
      "흥국생명": 4905,
      "KB라이프": 4603,
      "미래에셋": 4371,
      "롯데손해보험": 4847,
      "신한라이프": 4030,
      "메리츠화재": 3672,
      "농협손해": 3591,
      "삼성화재": 5676
    },
    {
      "담보명": "질병상해(1~5종)수술비 (5종기준)",
      "가입금액": "300",
      "DB손해보험": 23075,
      "한화손해보험": 30231,
      "흥국화재": 26351,
      "하나손해": 29582,
      "현대해상화재": 30711,
      "KB손해보험": 21820,
      "ABL생명": 17970,
      "DB생명": 15560,
      "동양생명": 15928,
      "한화생명": 23310,
      "흥국생명": 17977,
      "KB라이프": 12336,
      "미래에셋": 15743,
      "롯데손해보험": 24684,
      "신한라이프": 19503,
      "메리츠화재": 21209,
      "농협손해": 18916,
      "삼성화재": 30868
    },
    {
      "담보명": "상해 및 질병 1인실 종합병원(상급)",
      "가입금액": "20",
      "DB손해보험": 2184,
      "한화손해보험": 758,
      "흥국화재": 1220,
      "하나손해": 1320,
      "현대해상화재": 1180,
      "KB손해보험": 690,
      "DB생명": 1860,
      "동양생명": 1000,
      "한화생명": 940,
      "흥국생명": 1080,
      "KB라이프": 680,
      "미래에셋": 2260,
      "롯데손해보험": 3480,
      "신한라이프": 2960,
      "메리츠화재": 994,
      "농협손해": 3980,
      "삼성화재": 940
    },
    {
      "담보명": "상해및질병 2~3인실 종합병원(상급)",
      "가입금액": "20",
      "DB손해보험": 3340,
      "한화손해보험": 10920,
      "흥국화재": 6370,
      "하나손해": 14480,
      "현대해상화재": 7320,
      "KB손해보험": 5500,
      "DB생명": 5740,
      "동양생명": 4580,
      "한화생명": 2880,
      "흥국생명": 4100,
      "KB라이프": 2260,
      "미래에셋": 3660,
      "롯데손해보험": 9620,
      "신한라이프": 2840,
      "메리츠화재": 7140,
      "농협손해": 10160,
      "삼성화재": 6940
    },
    {
      "담보명": "상해 및 질병 1인실 종합병원",
      "가입금액": "10",
      "DB손해보험": 2700,
      "한화손해보험": 7220,
      "흥국화재": 2230,
      "하나손해": 1860,
      "현대해상화재": 1500,
      "KB손해보험": 1940,
      "DB생명": 2980,
      "동양생명": 1410,
      "한화생명": 1110,
      "흥국생명": 1980,
      "KB라이프": 980,
      "미래에셋": 1780,
      "롯데손해보험": 4200,
      "신한라이프": 2210,
      "메리츠화재": 1710,
      "농협손해": 4440,
      "삼성화재": 1360
    },
    {
      "담보명": "상해및질병 2~3인실 종합병원",
      "가입금액": "10",
      "DB손해보험": 6350,
      "한화손해보험": 18540,
      "흥국화재": 9450,
      "하나손해": 18000,
      "현대해상화재": 9570,
      "KB손해보험": 9030,
      "DB생명": 9070,
      "동양생명": 5840,
      "한화생명": 3000,
      "흥국생명": 4010,
      "KB라이프": 2230,
      "미래에셋": 3950,
      "롯데손해보험": 11150,
      "신한라이프": 2800,
      "메리츠화재": 11850,
      "농협손해": 12160,
      "삼성화재": 9010
    },
    {
      "담보명": "암직접치료입원일당(1-180,요양병원제외) 1만원",
      "가입금액": "2",
      "DB손해보험": 5620,
      "한화손해보험": 5168,
      "흥국화재": 3956,
      "하나손해": 3580,
      "현대해상화재": 5568,
      "KB손해보험": 4206,
      "동양생명": 3034,
      "KB라이프": 2940,
      "미래에셋": 2882,
      "롯데손해보험": 3918,
      "신한라이프": 3516,
      "메리츠화재": 3898,
      "농협손해": 5658,
      "삼성화재": 4954
    },
    {
      "담보명": "암요양병원입원비(1~90) 1만원",
      "가입금액": "1",
      "DB손해보험": 783,
      "한화손해보험": 870,
      "흥국화재": 550,
      "하나손해": 818,
      "현대해상화재": 783,
      "KB손해보험": 542,
      "동양생명": 277,
      "KB라이프": 367,
      "미래에셋": 278,
      "롯데손해보험": 540,
      "신한라이프": 728,
      "메리츠화재": 566,
      "농협손해": 890,
      "삼성화재": 736
    },
    {
      "담보명": "암통원일당(1만원 기준)",
      "가입금액": "2",
      "DB손해보험": 6164,
      "한화손해보험": 3800,
      "하나손해": 2524,
      "KB손해보험": 8418,
      "동양생명": 1118,
      "한화생명": 1302,
      "흥국생명": 4450,
      "KB라이프": 3810,
      "미래에셋": 1498,
      "롯데손해보험": 5984,
      "신한라이프": 1446,
      "농협손해": 4624,
      "삼성화재": 4878
    },
    {
      "담보명": "암통원일당(상급종합병원)(1만원 기준)",
      "가입금액": "10",
      "DB손해보험": 16950,
      "한화손해보험": 12720,
      "흥국화재": 10770,
      "하나손해": 15410,
      "현대해상화재": 18680,
      "KB손해보험": 24140,
      "동양생명": 6390,
      "한화생명": 4390,
      "흥국생명": 11290,
      "KB라이프": 11430,
      "롯데손해보험": 17010,
      "신한라이프": 3710,
      "메리츠화재": 16630,
      "농협손해": 16090,
      "삼성화재": 14200
    },
    {
      "담보명": "뇌심통원일당(1만원 기준)",
      "가입금액": "2",
      "DB손해보험": 3980,
      "한화손해보험": 8528,
      "KB손해보험": 4572,
      "동양생명": 3750,
      "한화생명": 6896,
      "KB라이프": 4722,
      "신한라이프": 4886,
      "메리츠화재": 8576,
      "농협손해": 4688,
      "삼성화재": 2622
    },
    {
      "담보명": "뇌심통원일당(상급종합병원)(1만원 기준)",
      "가입금액": "10",
      "DB손해보험": 5270,
      "KB손해보험": 6210,
      "동양생명": 5370,
      "한화생명": 8820,
      "KB라이프": 6630,
      "신한라이프": 5780,
      "메리츠화재": 12250,
      "농협손해": 6540,
      "삼성화재": 3850
    },
    {
      "담보명": "질병상해입원비(1만원 기준)",
      "가입금액": "1",
      "DB손해보험": 16330,
      "한화손해보험": 31670,
      "흥국화재": 20759,
      "하나손해": 17405,
      "현대해상화재": 17531,
      "KB손해보험": 17316,
      "동양생명": 9794,
      "한화생명": 11340,
      "흥국생명": 9047,
      "KB라이프": 8161,
      "미래에셋": 11968,
      "롯데손해보험": 20187,
      "신한라이프": 12361,
      "메리츠화재": 17448,
      "농협손해": 19044,
      "삼성화재": 14996
    },
    {
      "담보명": "질병상해중환자실입원비(1만원 기준)",
      "가입금액": "2",
      "DB손해보험": 614,
      "한화손해보험": 842,
      "흥국화재": 742,
      "하나손해": 502,
      "현대해상화재": 526,
      "KB손해보험": 402,
      "동양생명": 846,
      "흥국생명": 766,
      "KB라이프": 538,
      "미래에셋": 1044,
      "롯데손해보험": 596,
      "신한라이프": 936,
      "메리츠화재": 466,
      "농협손해": 718,
      "삼성화재": 830
    },
    {
      "담보명": "통풍진단비",
      "가입금액": "30",
      "DB손해보험": 1638,
      "한화손해보험": 1011,
      "흥국화재": 810,
      "하나손해": 813,
      "현대해상화재": 948,
      "KB손해보험": 1320,
      "ABL생명": 41,
      "한화생명": 568,
      "흥국생명": 822,
      "미래에셋": 471,
      "신한라이프": 525,
      "메리츠화재": 864,
      "농협손해": 744,
      "삼성화재": 903
    },
    {
      "담보명": "대상포진진단비",
      "가입금액": "30",
      "DB손해보험": 2118,
      "한화손해보험": 2052,
      "흥국화재": 2496,
      "하나손해": 1548,
      "현대해상화재": 1680,
      "KB손해보험": 1704,
      "ABL생명": 107,
      "한화생명": 1481,
      "흥국생명": 2343,
      "미래에셋": 987,
      "신한라이프": 1161,
      "메리츠화재": 2790,
      "농협손해": 2043,
      "삼성화재": 1917
    },
    {
      "담보명": "질병사망",
      "가입금액": "1000",
      "한화손해보험": 27960,
      "흥국화재": 20070,
      "하나손해": 16170,
      "현대해상화재": 26038,
      "KB손해보험": 32000,
      "롯데손해보험": 19800,
      "메리츠화재": 16660,
      "농협손해": 18770,
      "삼성화재": 19450
    },
    {
      "담보명": "중증질환자암산정특례대상진단",
      "가입금액": "200",
      "한화손해보험": 9182,
      "흥국화재": 4916,
      "하나손해": 6212,
      "현대해상화재": 8469,
      "KB손해보험": 4928,
      "DB생명": 3860,
      "동양생명": 7186,
      "롯데손해보험": 6592,
      "신한라이프": 6894,
      "삼성화재": 4328
    },
    {
      "담보명": "암상급종합병원주요치료비(만기보장)",
      "가입금액": "1000",
      "한화손해보험": 70608,
      "흥국화재": 75750,
      "현대해상화재": 64986,
      "KB손해보험": 64252,
      "한화생명": 76440,
      "미래에셋": 45086,
      "롯데손해보험": 61090,
      "신한라이프": 52470,
      "삼성화재": 53952
    },
    {
      "담보명": "카티(CAR-T)항암약물허가치료비",
      "가입금액": "1000",
      "한화손해보험": 55,
      "흥국화재": 470,
      "하나손해": 28,
      "현대해상화재": 302,
      "KB손해보험": 270,
      "ABL생명": 50,
      "DB생명": 20,
      "흥국생명": 720,
      "롯데손해보험": 46,
      "신한라이프": 118
    },
    {
      "담보명": "순환계주요치료비(만기보장)상급종합병원",
      "가입금액": "1000",
      "한화손해보험": 29100,
      "KB손해보험": 20150,
      "KB라이프": 23730,
      "롯데손해보험": 16250,
      "신한라이프": 24900,
      "삼성화재": 21910
    },
    {
      "담보명": "2대질환주요치료비(만기보장)",
      "가입금액": "1000",
      "한화손해보험": 20770,
      "흥국화재": 35300,
      "현대해상화재": 38440,
      "KB손해보험": 38150,
      "한화생명": 65720,
      "흥국생명": 15200,
      "KB라이프": 28610,
      "롯데손해보험": 38130,
      "농협손해": 17230
    },
    {
      "담보명": "2대질환상급종합병원주요치료비(만기보장)",
      "가입금액": "1000",
      "한화손해보험": 9460,
      "현대해상화재": 18920,
      "KB손해보험": 13890,
      "KB라이프": 12760,
      "롯데손해보험": 16360,
      "삼성화재": 19400
    },
    {
      "담보명": "암주요치료비(만기보장)",
      "가입금액": "1000",
      "흥국화재": 97080,
      "현대해상화재": 91036,
      "ABL생명": 65768,
      "한화생명": 92210,
      "흥국생명": 51420,
      "미래에셋": 60370,
      "롯데손해보험": 92668
    },
    {
      "담보명": "2대질환주요치료비(10년)",
      "가입금액": "1000",
      "흥국화재": 13260,
      "하나손해": 37600,
      "KB손해보험": 14480,
      "ABL생명": 37520,
      "DB생명": 29460,
      "동양생명": 22509,
      "KB라이프": 22070,
      "미래에셋": 25270,
      "롯데손해보험": 16040,
      "신한라이프": 30750,
      "메리츠화재": 38130,
      "농협손해": 9930,
      "삼성화재": 31010
    },
    {
      "담보명": "2대질환상급종합병원주요치료비(10년)",
      "가입금액": "1000",
      "하나손해": 16620,
      "동양생명": 10545,
      "KB라이프": 10260,
      "미래에셋": 12010,
      "롯데손해보험": 7470,
      "신한라이프": 14510,
      "메리츠화재": 17050,
      "삼성화재": 14290
    },
    {
      "담보명": "주계약",
      "가입금액": "100",
      "ABL생명": 3480,
      "DB생명": 3330,
      "동양생명": 3465,
      "한화생명": 3800,
      "흥국생명": 2540,
      "KB라이프": 3780,
      "미래에셋": 3241,
      "신한라이프": 4359
    },
    {
      "담보명": "암직접치료입원일당(1-180,요양병원제외) 1000만원",
      "가입금액": "2000",
      "ABL생명": 16520
    },
    {
      "담보명": "암요양병원입원비(1~90) 1000만원",
      "가입금액": "1000",
      "ABL생명": 830
    },
    {
      "담보명": "암통원일당(1000만원 기준)",
      "가입금액": "2000",
      "ABL생명": 8120,
      "DB생명": 2780
    },
    {
      "담보명": "암통원일당(상급종합병원)(1000만원 기준)",
      "가입금액": "1000",
      "ABL생명": 2610,
      "DB생명": 830
    },
    {
      "담보명": "뇌심통원일당(1000만원 기준)",
      "가입금액": "1000",
      "ABL생명": 1570,
      "DB생명": 5240
    },
    {
      "담보명": "뇌심통원일당(상급종합병원)(1000만원 기준)",
      "가입금액": "1000",
      "ABL생명": 2490
    },
    {
      "담보명": "질병상해입원비(1000만원 기준)",
      "가입금액": "1000",
      "ABL생명": 8700,
      "DB생명": 15310
    },
    {
      "담보명": "상해질병수술비",
      "가입금액": "10",
      "한화생명": 5742
    },
    {
      "담보명": "합계",
      "가입금액": "nan",
      "DB손해보험": 768613,
      "한화손해보험": 906600,
      "흥국화재": 884171,
      "하나손해": 712394,
      "현대해상화재": 828409,
      "KB손해보험": 846621,
      "ABL생명": 503296,
      "DB생명": 372606,
      "동양생명": 343096,
      "한화생명": 678072,
      "흥국생명": 424686,
      "KB라이프": 635242,
      "미래에셋": 605197,
      "롯데손해보험": 950501,
      "신한라이프": 605102,
      "메리츠화재": 644285,
      "농협손해": 777648,
      "삼성화재": 766068
    }
  ],
  "productData": {
    "DB손해보험": "무)나에게맞춘간편건강보험2604",
    "한화손해보험": "무)3N5 더간편건강보험(세만기형)2604",
    "흥국화재": "무)흥Good 든든한 3N5 간편종합보험(26.04)",
    "하나손해": "무)하나더퍼스트 3N5 간편건강보험(2604)",
    "현대해상화재": "무)오투(O2)맞춤간편건강보험(HI2601)",
    "KB손해보험": "무)3.N.5)슬기로운 간편건강보험Plus(26.01)",
    "ABL생명": "무)우리WON건강N더보장종합보험",
    "DB생명": "무)백년친구NEW간편N내가고른건강보험",
    "동양생명": "무)우리WON하는간편한보장보험",
    "한화생명": "무)시그니처 H통합건강보험",
    "흥국생명": "무)다사랑335간편건강보험",
    "KB라이프": "무)KB3.N.5딱좋은요즘건강보험",
    "미래에셋": "무)M-케어 건강보험",
    "롯데손해보험": "무)let:simple 3N5 간편맞춤 건강보험(2604)",
    "신한라이프": "무)신한통합건강보장보험 원(ONE)",
    "메리츠화재": "무)통합간편건강보험(II)2604(통합간편심사형)",
    "농협손해": "무)NH335 굿패스건강보험2604",
    "삼성화재": "무)간편보험 새로고침100세(2601.6)"
  }
}